pybea/__init__.py
pybea/client.py
python_bea-0.1.1.dist-info/LICENSE
python_bea-0.1.1.dist-info/METADATA
python_bea-0.1.1.dist-info/WHEEL
python_bea-0.1.1.dist-info/top_level.txt
python_bea-0.1.1.dist-info/RECORD
