Metadata-Version: 2.1
Name: python-bea
Version: 0.1.1
Summary: A python API client library for the US Bureau of Economic Analysis
Home-page: https://github.com/areed1192/python-bureau-economic-analysis-api-client.git
Author: Alex Reed
Author-email: coding.sigma@gmail.com
License: UNKNOWN
Platform: UNKNOWN
Classifier: Development Status :: 3 - Alpha
Classifier: Intended Audience :: Financial and Insurance Industry
Classifier: License :: OSI Approved :: MIT License
Classifier: Natural Language :: English
Classifier: Operating System :: OS Independent
Classifier: Programming Language :: Python :: 3
Requires-Python: >3.8
License-File: LICENSE
Requires-Dist: requests
